[{"key":"10.jpg","url":"images\/10.jpg"},{"key":"11.jpg","url":"images\/11.jpg"},{"key":"12.jpg","url":"images\/12.jpg"},{"key":"13.jpg","url":"images\/13.jpg"},{"key":"14.jpg","url":"images\/14.jpg"},{"key":"15.jpg","url":"images\/15.jpg"},{"key":"16.jpg","url":"images\/16.jpg"},{"key":"17.jpg","url":"images\/17.jpg"},{"key":"18.jpg","url":"images\/18.jpg"},{"key":"19.jpg","url":"images\/19.jpg"},{"key":"20.jpg","url":"images\/20.jpg"},{"key":"21.jpg","url":"images\/21.jpg"},{"key":"22.jpg","url":"images\/22.jpg"},{"key":"23.jpg","url":"images\/23.jpg"},{"key":"24.jpg","url":"images\/24.jpg"},{"key":"25.jpg","url":"images\/25.jpg"},{"key":"26.jpg","url":"images\/26.jpg"},{"key":"27.jpg","url":"images\/27.jpg"},{"key":"28.jpg","url":"images\/28.jpg"},{"key":"29.jpg","url":"images\/29.jpg"},{"key":"3.jpg","url":"images\/3.jpg"},{"key":"30.jpg","url":"images\/30.jpg"},{"key":"31.jpg","url":"images\/31.jpg"},{"key":"32.jpg","url":"images\/32.jpg"},{"key":"33.jpg","url":"images\/33.jpg"},{"key":"34.jpg","url":"images\/34.jpg"},{"key":"35.jpg","url":"images\/35.jpg"},{"key":"36.jpg","url":"images\/36.jpg"},{"key":"37.jpg","url":"images\/37.jpg"},{"key":"38.jpg","url":"images\/38.jpg"},{"key":"39.jpg","url":"images\/39.jpg"},{"key":"4.jpg","url":"images\/4.jpg"},{"key":"40.jpg","url":"images\/40.jpg"},{"key":"41.jpg","url":"images\/41.jpg"},{"key":"42.jpg","url":"images\/42.jpg"},{"key":"43.jpg","url":"images\/43.jpg"},{"key":"44.jpg","url":"images\/44.jpg"},{"key":"45.jpg","url":"images\/45.jpg"},{"key":"46.jpg","url":"images\/46.jpg"},{"key":"47.jpg","url":"images\/47.jpg"},{"key":"48.jpg","url":"images\/48.jpg"},{"key":"49.jpg","url":"images\/49.jpg"},{"key":"5.jpg","url":"images\/5.jpg"},{"key":"50.jpg","url":"images\/50.jpg"},{"key":"51.jpg","url":"images\/51.jpg"},{"key":"6.jpg","url":"images\/6.jpg"},{"key":"7.jpg","url":"images\/7.jpg"},{"key":"8.jpg","url":"images\/8.jpg"},{"key":"9.jpg","url":"images\/9.jpg"}]